n4s/__init__.py
n4s/fs.py
n4s/strgs.py
n4s/term.py
n4s/web.py
n4s-2.4.3.dist-info/LICENSE
n4s-2.4.3.dist-info/METADATA
n4s-2.4.3.dist-info/WHEEL
n4s-2.4.3.dist-info/top_level.txt
n4s-2.4.3.dist-info/RECORD
